{
  "project_info": {
    "project_number": "126453952717",
    "project_id": "ai-todolist-36a96",
    "storage_bucket": "ai-todolist-36a96.firebasestorage.app"
  },
  "client": [
    {
      "client_info": {
        "mobilesdk_app_id": "1:126453952717:android:8798ff86b71730b5b43984",
        "android_client_info": {
          "package_name": "com.example.aiassistant1"
        }
      },
      "oauth_client": [
        {
          "client_id": "126453952717-asrtr6v7f3b3elp4tdbt35n1eq69kn8d.apps.googleusercontent.com",
          "client_type": 3
        }
      ],
      "api_key": [
        {
          "current_key": "AIzaSyAUF3bI7TJYJP-H2n98HOBy0pwr9BH8_OI"
        }
      ],
      "services": {
        "appinvite_service": {
          "other_platform_oauth_client": [
            {
              "client_id": "126453952717-asrtr6v7f3b3elp4tdbt35n1eq69kn8d.apps.googleusercontent.com",
              "client_type": 3
            },
            {
              "client_id": "126453952717-dbdfdlgcfueoj7piasjna7nkdgk6obmk.apps.googleusercontent.com",
              "client_type": 2,
              "ios_info": {
                "bundle_id": "com.example.aiassistant1"
              }
            }
          ]
        }
      }
    }
  ],
  "configuration_version": "1"
}